hello_richa_utils/__init__.py
hello_richa_utils-0.1.3.dist-info/METADATA
hello_richa_utils-0.1.3.dist-info/WHEEL
hello_richa_utils-0.1.3.dist-info/RECORD
