Metadata-Version: 2.4
Name: hello_richa_utils
Version: 0.1.3
Summary: A package to say hello
Project-URL: Homepage, https://github.com/Engage-Infra-ITH/helloutils
Author-email: Engage-Infra <richa.sharma@ttec.com>
License-Expression: MIT
